__init__.py
main.py
cli/__init__.py
cli/cli.py
login/__init__.py
login/login.py
scraping/__init__.py
scraping/scraper.py
unitn_course_scraper-0.1.6.dist-info/LICENSE
unitn_course_scraper-0.1.6.dist-info/METADATA
unitn_course_scraper-0.1.6.dist-info/WHEEL
unitn_course_scraper-0.1.6.dist-info/entry_points.txt
unitn_course_scraper-0.1.6.dist-info/top_level.txt
unitn_course_scraper-0.1.6.dist-info/RECORD
