Metadata-Version: 2.1
Name: unitn-course-scraper
Version: 0.1.6
Summary: Interactive scraper for your UniTN courses
Author-email: DISI Drive Team <unitndrive@gmail.com>
Keywords: unitn,courses,scraper,@unitn.it,moodle,dol,gestionecorsi,didatticaonline
Classifier: Programming Language :: Python :: 3.7
Classifier: Programming Language :: Python :: 3.8
Classifier: Programming Language :: Python :: 3.9
Classifier: Programming Language :: Python :: 3.10
Classifier: License :: OSI Approved :: GNU General Public License v3 (GPLv3)
Classifier: Operating System :: OS Independent
Requires-Python: >=3.7
License-File: LICENSE
Requires-Dist: python-dotenv (>=1.0.0)
Requires-Dist: requests (>=2.28.2)
Requires-Dist: grequests (>=0.6.0)
Requires-Dist: beautifulsoup4 (>=4.12.2)
